storygraph_api/__init__.py
storygraph_api/books_client.py
storygraph_api/exception_handler.py
storygraph_api/exceptions.py
storygraph_api/users_client.py
storygraph_api/parse/__init__.py
storygraph_api/parse/books_parser.py
storygraph_api/parse/user_parser.py
storygraph_api/request/__init__.py
storygraph_api/request/books_request.py
storygraph_api/request/user_request.py
test/__init__.py
test/test_request.py
storygraph_api-0.2.1.dist-info/LICENSE
storygraph_api-0.2.1.dist-info/METADATA
storygraph_api-0.2.1.dist-info/WHEEL
storygraph_api-0.2.1.dist-info/top_level.txt
storygraph_api-0.2.1.dist-info/RECORD
