Metadata-Version: 2.2
Name: storygraph-api
Version: 0.2.1
Summary: This package allows you to interact with and fetch data from the StoryGraph website.
Home-page: https://github.com/ym496/storygraph-api
Author: ym496
Author-email: yogendramishra2004@gmail.com
Keywords: storygraph,storygraph api,api storygraph,storygraph scraper
Classifier: Programming Language :: Python :: 3
Classifier: License :: OSI Approved :: MIT License
Classifier: Operating System :: OS Independent
Requires-Python: >=3.10
License-File: LICENSE
Requires-Dist: requests
Requires-Dist: beautifulsoup4
Requires-Dist: selenium
Dynamic: author
Dynamic: author-email
Dynamic: classifier
Dynamic: description
Dynamic: description-content-type
Dynamic: home-page
Dynamic: keywords
Dynamic: requires-dist
Dynamic: requires-python
Dynamic: summary
